pykoa/__init__.py
pykoa/koa/__init__.py
pykoa/koa/core.py
pykoa-1.7.2.dist-info/METADATA
pykoa-1.7.2.dist-info/WHEEL
pykoa-1.7.2.dist-info/top_level.txt
pykoa-1.7.2.dist-info/RECORD
