Metadata-Version: 2.1
Name: pykoa
Version: 1.7.2
Summary: KOA archive access client
Home-page: https://github.com/KeckObservatoryArchive/PyKOA
Author: Mihseh Kong
Author-email: mihseh@ipac.caltech.edu
License: UNKNOWN
Platform: UNKNOWN
Classifier: Intended Audience :: Science/Research
Classifier: Programming Language :: Python :: 3.6
Classifier: Programming Language :: Python :: 3.7
Classifier: License :: OSI Approved :: MIT License
Classifier: Topic :: Scientific/Engineering :: Astronomy
Requires-Python: >= 3.6
Requires-Dist: requests
Requires-Dist: xmltodict
Requires-Dist: bs4
Requires-Dist: lxml
